publ/__init__.py
publ/caching.py
publ/cards.py
publ/category.py
publ/cli.py
publ/config.py
publ/default_template/_admin.html
publ/default_template/error.html
publ/default_template/logout.html
publ/entry.py
publ/flask_wrapper.py
publ/html_entry.py
publ/image/__init__.py
publ/image/external.py
publ/image/image.py
publ/image/local.py
publ/index.py
publ/links.py
publ/maintenance.py
publ/markdown.py
publ/model.py
publ/path_alias.py
publ/queries.py
publ/rendering.py
publ/search.py
publ/template.py
publ/tokens.py
publ/user.py
publ/utils.py
publ/view.py
publ-0.8.6.dist-info/METADATA
publ-0.8.6.dist-info/WHEEL
publ-0.8.6.dist-info/licenses/LICENSE
publ-0.8.6.dist-info/RECORD
