Metadata-Version: 2.4
Name: Publ
Version: 0.8.6
Summary: A flexible web-based publishing framework
License: MIT
License-File: LICENSE
Author: fluffy
Author-email: fluffy@beesbuzz.biz
Requires-Python: >=3.9,<3.13
Classifier: License :: OSI Approved :: MIT License
Classifier: Programming Language :: Python :: 3
Classifier: Programming Language :: Python :: 3.9
Classifier: Programming Language :: Python :: 3.10
Classifier: Programming Language :: Python :: 3.11
Classifier: Programming Language :: Python :: 3.12
Provides-Extra: auth
Provides-Extra: search
Requires-Dist: Flask (>=3.1.0,<4.0.0)
Requires-Dist: Flask-Caching (>=2.3.0,<3.0.0)
Requires-Dist: Pygments (>=2.19.1,<3.0.0)
Requires-Dist: arrow (>=1.3.0,<2.0.0)
Requires-Dist: atomicwrites (>=1.4.1,<2.0.0)
Requires-Dist: authl (>=0.7.0,<0.8.0) ; extra == "auth"
Requires-Dist: awesome-slugify (>=1.6.5,<2.0.0)
Requires-Dist: beautifulsoup4 (>=4.14.0,<5.0.0)
Requires-Dist: misaka (>=2.1.1,<3.0.0)
Requires-Dist: pillow (>=11.1.0,<12.0.0)
Requires-Dist: pony (>=0.7.19,<0.8.0)
Requires-Dist: requests (>=2.32.3,<3.0.0)
Requires-Dist: watchdog
Requires-Dist: whoosh-reloaded (>=2.7.4,<3.0.0) ; extra == "search"
Project-URL: Homepage, https://publ.plaidweb.site/
Project-URL: Repository, https://github.com/PlaidWeb/Publ
